README.md
setup.py
estimator/__init__.py
estimator/clips.py
estimator/decays.py
estimator/losses.py
estimator/metrics.py
estimator/models.py
estimator/modes.py
estimator/optimizers.py
estimator/training.py
estimator/utils.py
estimator.egg-info/PKG-INFO
estimator.egg-info/SOURCES.txt
estimator.egg-info/dependency_links.txt
estimator.egg-info/not-zip-safe
estimator.egg-info/top_level.txt